enable_log_streaming/__init__.py
enable_log_streaming/enable_log_streaming.py
enable_log_streaming_MithunChandrasekar-0.0.2.dist-info/LICENSE
enable_log_streaming_MithunChandrasekar-0.0.2.dist-info/METADATA
enable_log_streaming_MithunChandrasekar-0.0.2.dist-info/WHEEL
enable_log_streaming_MithunChandrasekar-0.0.2.dist-info/top_level.txt
enable_log_streaming_MithunChandrasekar-0.0.2.dist-info/RECORD
