Metadata-Version: 2.1
Name: enable-log-streaming-MithunChandrasekar
Version: 0.0.2
Summary: A library to enable log streaming for Elastic Beanstalk environments.
Home-page: https://github.com/MithunChandrasekar/enable-log-streaming-MithunChandrasekar
Author: Mithun Chandrasekar
Author-email: mithunxchandrasekar1@gmail.com
Classifier: Programming Language :: Python :: 3
Classifier: License :: OSI Approved :: MIT License
Classifier: Operating System :: OS Independent
Requires-Python: >=3.6
License-File: LICENSE
Requires-Dist: boto3>=1.20.0
